pass50/__init__.py
pass50/args.py
pass50/cmd50.py
pass50/color.py
pass50/runner50.py
pass50-0.0.3.dist-info/LICENSE
pass50-0.0.3.dist-info/METADATA
pass50-0.0.3.dist-info/WHEEL
pass50-0.0.3.dist-info/entry_points.txt
pass50-0.0.3.dist-info/top_level.txt
pass50-0.0.3.dist-info/RECORD
