Metadata-Version: 2.1
Name: pass50
Version: 0.0.3
Summary: A convinent tool to check and submit your codes to "CS50".
Author-email: zivmax <zivmax@foxmail.com>
Maintainer-email: zivmax <zivmax@foxmail.com>
Project-URL: Repository, https://github.com/zivmax/pass50
Project-URL: Issues, https://github.com/zivmax/pass50/issues
Classifier: Programming Language :: Python :: 3
Classifier: License :: OSI Approved :: GNU General Public License v3 (GPLv3)
Classifier: Operating System :: POSIX :: Linux
Requires-Python: >=3.10
License-File: LICENSE
Requires-Dist: cowsay
Requires-Dist: colorama
